rivr/__init__.py
rivr/http/__init__.py
rivr/http/message.py
rivr/http/request.py
rivr/http/response.py
rivr/importlib.py
rivr/middleware/__init__.py
rivr/middleware/auth.py
rivr/middleware/base.py
rivr/middleware/debug.py
rivr/py.typed
rivr/router.py
rivr/server.py
rivr/sessions.py
rivr/test.py
rivr/views/__init__.py
rivr/views/base.py
rivr/views/static.py
rivr/wsgi.py
rivr-0.10.0.dist-info/LICENSE
rivr-0.10.0.dist-info/METADATA
rivr-0.10.0.dist-info/WHEEL
rivr-0.10.0.dist-info/RECORD
